redb-0.5.0.dist-info/METADATA
redb-0.5.0.dist-info/WHEEL
redb-0.5.0.dist-info/license_files/LICENSE-APACHE
redb-0.5.0.dist-info/license_files/LICENSE-MIT
redb/__init__.py
redb/redb.abi3.so
redb-0.5.0.dist-info/RECORD
