Metadata-Version: 2.1
Name: redb
Version: 0.5.0
Classifier: Development Status :: 4 - Beta
Classifier: License :: OSI Approved :: MIT License
Classifier: License :: OSI Approved :: Apache Software License
Classifier: Programming Language :: Python
Classifier: Programming Language :: Python :: 3
Classifier: Programming Language :: Python :: 3 :: Only
Classifier: Programming Language :: Rust
License-File: LICENSE-APACHE
License-File: LICENSE-MIT
Summary: Rust Embedded DataBase
Home-Page: https://www.redb.org
Author: Christopher Berner <christopherberner@gmail.com>
Author-email: Christopher Berner <christopherberner@gmail.com>
License: MIT OR Apache-2.0
Requires-Python: >=3.7
Project-URL: Source Code, https://github.com/cberner/redb
